{
    "bvid": "BV16b411q7Nv",
    "aid": 45579003,
    "videos": 1,
    "tid": 253,
    "tname": "动漫杂谈",
    "copyright": 1,
    "pic": "http://i1.hdslb.com/bfs/archive/b977e9355a99187e56d40d4e60bbf33787b0e4d6.jpg",
    "title": "恋爱酸臭！阿伟死期！光头进击！2019年四月新番导视",
    "pubdate": 1551941876,
    "ctime": 1551941877,
    "desc": "微博@凉风Kaze\n每天起床第一句，长按点赞一条龙。\n\n四月新番放送时间表如下（仅供参考）：\n\n3月1日\n加农炮破坏者\n\n4月1日\nULTRAMAN（机动奥特曼）\npop子和pipi美 电视特别新作\n爆丸战斗行星\n\n4月2日\n钻石王牌ACT2\n在世界尽头咏唱恋曲的少女YU-NO\n\n4月3日\n一拳超人第二季\n\n4月4日\n八十龟的观察日记\n\n4月5日\nBAKUMATSU CRISIS（恋爱幕末男友第二季）\n妖怪手表\n\n4月6日\n水果篮子重制版\n川柳少女\n满脑都是○○的我没办法谈恋爱\n孤独的躲在墙角画圈圈\n地狱公路巡警\n超可动女孩1/6 \n默绘女高\n信长老师的年幼妻子\n鬼灭之刃\n\n4月7日\n我们真的学不来（我们无法一起学习）\n一弦定音！\n小公主索菲亚 新系列\n拾又之国\n消灭都市\n洗屋先生！～我和那家伙在女浴池！?～\n\n4月8日\n八月的灰姑娘棒球队\n南无阿弥陀佛!-莲台UTENA-\n\n4月9日\nKING OF PRISM -Shiny Seven Stars-\n强袭魔女：501部队出发！\n\n4月10日\n贤者之孙\n\n4月11日\nCAROLE & TUESDAY\n\n4月19日\n轻松小熊和小薰\n\n4月29日\n进击的巨人第三季后半季\n机动战士高达the origin前夜红彗星\n\n4月X日（暂未定具体日期）\nMIX\n美妙频道第二季\n偶像活动Friends!～闪耀的宝石～\nジモトがジャパン（都道府拳）\nBラッパーズ ストリート\n叛逆性百万亚瑟王第二季\n皿三昧\n为什么老师会在这里？\n哇！～我们小动物爱护委员会～\n深夜的超自然公务员\n偶像大师：灰姑娘女孩剧场 CLIMAX SEASON\n文豪野犬第三季\nRobiHachi\nFairy gone \n贤惠幼妻仙狐小姐\n\n4月-6月\n卡片战斗先导者 续・高校生編\nけだまのゴンじろー\n异世界四重奏\n7seeds",
    "desc_v2": [
        {
            "raw_text": "微博@凉风Kaze\n每天起床第一句，长按点赞一条龙。\n\n四月新番放送时间表如下（仅供参考）：\n\n3月1日\n加农炮破坏者\n\n4月1日\nULTRAMAN（机动奥特曼）\npop子和pipi美 电视特别新作\n爆丸战斗行星\n\n4月2日\n钻石王牌ACT2\n在世界尽头咏唱恋曲的少女YU-NO\n\n4月3日\n一拳超人第二季\n\n4月4日\n八十龟的观察日记\n\n4月5日\nBAKUMATSU CRISIS（恋爱幕末男友第二季）\n妖怪手表\n\n4月6日\n水果篮子重制版\n川柳少女\n满脑都是○○的我没办法谈恋爱\n孤独的躲在墙角画圈圈\n地狱公路巡警\n超可动女孩1/6 \n默绘女高\n信长老师的年幼妻子\n鬼灭之刃\n\n4月7日\n我们真的学不来（我们无法一起学习）\n一弦定音！\n小公主索菲亚 新系列\n拾又之国\n消灭都市\n洗屋先生！～我和那家伙在女浴池！?～\n\n4月8日\n八月的灰姑娘棒球队\n南无阿弥陀佛!-莲台UTENA-\n\n4月9日\nKING OF PRISM -Shiny Seven Stars-\n强袭魔女：501部队出发！\n\n4月10日\n贤者之孙\n\n4月11日\nCAROLE & TUESDAY\n\n4月19日\n轻松小熊和小薰\n\n4月29日\n进击的巨人第三季后半季\n机动战士高达the origin前夜红彗星\n\n4月X日（暂未定具体日期）\nMIX\n美妙频道第二季\n偶像活动Friends!～闪耀的宝石～\nジモトがジャパン（都道府拳）\nBラッパーズ ストリート\n叛逆性百万亚瑟王第二季\n皿三昧\n为什么老师会在这里？\n哇！～我们小动物爱护委员会～\n深夜的超自然公务员\n偶像大师：灰姑娘女孩剧场 CLIMAX SEASON\n文豪野犬第三季\nRobiHachi\nFairy gone \n贤惠幼妻仙狐小姐\n\n4月-6月\n卡片战斗先导者 续・高校生編\nけだまのゴンじろー\n异世界四重奏\n7seeds",
            "type": 1,
            "biz_id": 0
        }
    ],
    "state": 0,
    "duration": 724,
    "rights": {
        "bp": 0,
        "elec": 0,
        "download": 1,
        "movie": 0,
        "pay": 0,
        "hd5": 1,
        "no_reprint": 1,
        "autoplay": 1,
        "ugc_pay": 0,
        "is_cooperation": 0,
        "ugc_pay_preview": 0,
        "no_background": 0,
        "clean_mode": 0,
        "is_stein_gate": 0,
        "is_360": 0,
        "no_share": 0,
        "arc_pay": 0,
        "free_watch": 0
    },
    "owner": {
        "mid": 14110780,
        "name": "凉风Kaze",
        "face": "https://i1.hdslb.com/bfs/face/e0cc906bb531195e9ee9f3b575effdd2b056eaea.jpg"
    },
    "stat": {
        "aid": 45579003,
        "view": 819521,
        "danmaku": 5726,
        "reply": 2023,
        "favorite": 15902,
        "coin": 26410,
        "share": 3296,
        "now_rank": 0,
        "his_rank": 15,
        "like": 39492,
        "dislike": 0,
        "evaluation": "",
        "argue_msg": "",
        "vt": 0
    },
    "dynamic": "#凉风Kaze#恋爱酸臭！阿伟死期！光头进击！2019年四月#新番导视#",
    "cid": 79808099,
    "dimension": {
        "width": 1920,
        "height": 1080,
        "rotate": 0
    },
    "premiere": null,
    "teenage_mode": 0,
    "is_chargeable_season": false,
    "is_story": false,
    "is_upower_exclusive": false,
    "is_upower_play": false,
    "enable_vt": 0,
    "vt_display": "",
    "no_cache": false,
    "pages": [
        {
            "cid": 79808099,
            "page": 1,
            "from": "vupload",
            "part": "进击",
            "duration": 724,
            "vid": "",
            "weblink": "",
            "dimension": {
                "width": 1920,
                "height": 1080,
                "rotate": 0
            }
        }
    ],
    "subtitle": {
        "allow_submit": false,
        "list": []
    },
    "is_season_display": false,
    "user_garb": {
        "url_image_ani_cut": ""
    },
    "honor_reply": {
        "honor": [
            {
                "aid": 45579003,
                "type": 3,
                "desc": "全站排行榜最高第15名",
                "weekly_recommend_num": 0
            }
        ]
    },
    "like_icon": "",
    "need_jump_bv": false,
    "disable_show_up_info": false
}