{
    "bvid": "BV19U4y1x7QA",
    "aid": 671121668,
    "videos": 1,
    "tid": 138,
    "tname": "搞笑",
    "copyright": 1,
    "pic": "http://i0.hdslb.com/bfs/archive/65ceff32b539b838b23a527a38a8c6ecd616a37e.jpg",
    "title": "万恶之源！你一定见过这些表情包",
    "pubdate": 1610200819,
    "ctime": 1610200820,
    "desc": "还真TM全是名场面！\n更多生活中的凉风详见微博@凉风Kaze",
    "desc_v2": [
        {
            "raw_text": "还真TM全是名场面！\n更多生活中的凉风详见微博@凉风Kaze",
            "type": 1,
            "biz_id": 0
        }
    ],
    "state": 0,
    "duration": 560,
    "rights": {
        "bp": 0,
        "elec": 0,
        "download": 1,
        "movie": 0,
        "pay": 0,
        "hd5": 1,
        "no_reprint": 1,
        "autoplay": 1,
        "ugc_pay": 0,
        "is_cooperation": 0,
        "ugc_pay_preview": 0,
        "no_background": 0,
        "clean_mode": 0,
        "is_stein_gate": 0,
        "is_360": 0,
        "no_share": 0,
        "arc_pay": 0,
        "free_watch": 0
    },
    "owner": {
        "mid": 14110780,
        "name": "凉风Kaze",
        "face": "https://i1.hdslb.com/bfs/face/e0cc906bb531195e9ee9f3b575effdd2b056eaea.jpg"
    },
    "stat": {
        "aid": 671121668,
        "view": 3701918,
        "danmaku": 8832,
        "reply": 3245,
        "favorite": 34087,
        "coin": 90759,
        "share": 4306,
        "now_rank": 0,
        "his_rank": 5,
        "like": 380680,
        "dislike": 0,
        "evaluation": "",
        "argue_msg": "",
        "vt": 0
    },
    "dynamic": "万恶之源！你一定见过这些表情包\n寒冷的冬天只有粉丝的三连能温暖凉仔的秃头（暗示）",
    "cid": 280059202,
    "dimension": {
        "width": 1920,
        "height": 1080,
        "rotate": 0
    },
    "premiere": null,
    "teenage_mode": 0,
    "is_chargeable_season": false,
    "is_story": false,
    "is_upower_exclusive": false,
    "is_upower_play": false,
    "enable_vt": 0,
    "vt_display": "",
    "no_cache": false,
    "pages": [
        {
            "cid": 280059202,
            "page": 1,
            "from": "vupload",
            "part": "万恶之源！你一定见过这些表情包",
            "duration": 560,
            "vid": "",
            "weblink": "",
            "dimension": {
                "width": 1920,
                "height": 1080,
                "rotate": 0
            }
        }
    ],
    "subtitle": {
        "allow_submit": false,
        "list": []
    },
    "is_season_display": false,
    "user_garb": {
        "url_image_ani_cut": ""
    },
    "honor_reply": {
        "honor": [
            {
                "aid": 671121668,
                "type": 2,
                "desc": "第95期每周必看",
                "weekly_recommend_num": 95
            },
            {
                "aid": 671121668,
                "type": 3,
                "desc": "全站排行榜最高第5名",
                "weekly_recommend_num": 0
            },
            {
                "aid": 671121668,
                "type": 4,
                "desc": "热门",
                "weekly_recommend_num": 0
            }
        ]
    },
    "like_icon": "",
    "need_jump_bv": false,
    "disable_show_up_info": false
}