{
    "bvid": "BV1hW411T7tf",
    "aid": 21578188,
    "videos": 1,
    "tid": 65,
    "tname": "网络游戏",
    "copyright": 1,
    "pic": "http://i2.hdslb.com/bfs/archive/1b7a2de59ced8e2282fe96ec1586a9fa12565e89.jpg",
    "title": "【老番茄】火星语吃鸡！RAP竟起源于中国？",
    "pubdate": 1522836057,
    "ctime": 1522836061,
    "desc": "相关游戏: 绝地求生\n简介补充: 我老番茄今天就来教大家如何RAP\n如果喜欢视频的话请多投币、多点赞、多收藏！收藏3w周更语言教学视频！！",
    "desc_v2": [
        {
            "raw_text": "相关游戏: 绝地求生\n简介补充: 我老番茄今天就来教大家如何RAP\n如果喜欢视频的话请多投币、多点赞、多收藏！收藏3w周更语言教学视频！！",
            "type": 1,
            "biz_id": 0
        }
    ],
    "state": 0,
    "duration": 456,
    "rights": {
        "bp": 0,
        "elec": 0,
        "download": 1,
        "movie": 0,
        "pay": 0,
        "hd5": 0,
        "no_reprint": 1,
        "autoplay": 1,
        "ugc_pay": 0,
        "is_cooperation": 0,
        "ugc_pay_preview": 0,
        "no_background": 0,
        "clean_mode": 0,
        "is_stein_gate": 0,
        "is_360": 0,
        "no_share": 0,
        "arc_pay": 0,
        "free_watch": 0
    },
    "owner": {
        "mid": 546195,
        "name": "老番茄",
        "face": "http://i0.hdslb.com/bfs/face/bc5ca101313d4db223c395d64779e76eb3482d60.jpg"
    },
    "stat": {
        "aid": 21578188,
        "view": 2820371,
        "danmaku": 14743,
        "reply": 3637,
        "favorite": 43814,
        "coin": 86951,
        "share": 13660,
        "now_rank": 0,
        "his_rank": 1,
        "like": 70259,
        "dislike": 0,
        "evaluation": "",
        "argue_msg": "",
        "vt": 0
    },
    "dynamic": "",
    "cid": 35543503,
    "dimension": {
        "width": 1920,
        "height": 1080,
        "rotate": 0
    },
    "premiere": null,
    "teenage_mode": 0,
    "is_chargeable_season": false,
    "is_story": false,
    "is_upower_exclusive": false,
    "is_upower_play": false,
    "enable_vt": 0,
    "vt_display": "",
    "no_cache": false,
    "pages": [
        {
            "cid": 35543503,
            "page": 1,
            "from": "vupload",
            "part": "",
            "duration": 456,
            "vid": "",
            "weblink": "",
            "dimension": {
                "width": 1920,
                "height": 1080,
                "rotate": 0
            }
        }
    ],
    "subtitle": {
        "allow_submit": false,
        "list": []
    },
    "is_season_display": false,
    "user_garb": {
        "url_image_ani_cut": ""
    },
    "honor_reply": {
        "honor": [
            {
                "aid": 21578188,
                "type": 3,
                "desc": "全站排行榜最高第1名",
                "weekly_recommend_num": 0
            }
        ]
    },
    "like_icon": "",
    "need_jump_bv": false,
    "disable_show_up_info": false
}