{
    "bvid": "BV1kA411c7Ky",
    "aid": 335182456,
    "videos": 1,
    "tid": 228,
    "tname": "人文历史",
    "copyright": 1,
    "pic": "http://i2.hdslb.com/bfs/archive/6f55501e69352969c4c58800f4e15295eb1ac0c6.jpg",
    "title": "人在美国如何当皇帝？【硬核狠人07】",
    "pubdate": 1630037584,
    "ctime": 1630037584,
    "desc": "本篇为硬核狠人篇之美国皇帝约书亚诺顿。\n\n参考文献 & 资料：\n1. 皇帝诺顿信托基金会官方网站\n2. 王清福传记\n3. 约翰·切赫写的传记\n4. 威廉·德鲁写的传记\n5. 罗伯特·考恩写的传记\n6. 科尔尼的演讲记录\n\n\n（虚晃一枪的创意来自 @刘老湿说电影）",
    "desc_v2": [
        {
            "raw_text": "本篇为硬核狠人篇之美国皇帝约书亚诺顿。\n\n参考文献 & 资料：\n1. 皇帝诺顿信托基金会官方网站\n2. 王清福传记\n3. 约翰·切赫写的传记\n4. 威廉·德鲁写的传记\n5. 罗伯特·考恩写的传记\n6. 科尔尼的演讲记录\n\n\n（虚晃一枪的创意来自 @刘老湿说电影）",
            "type": 1,
            "biz_id": 0
        }
    ],
    "state": 0,
    "duration": 1357,
    "mission_id": 118047,
    "rights": {
        "bp": 0,
        "elec": 0,
        "download": 1,
        "movie": 0,
        "pay": 0,
        "hd5": 0,
        "no_reprint": 1,
        "autoplay": 1,
        "ugc_pay": 0,
        "is_cooperation": 0,
        "ugc_pay_preview": 0,
        "no_background": 0,
        "clean_mode": 0,
        "is_stein_gate": 0,
        "is_360": 0,
        "no_share": 0,
        "arc_pay": 0,
        "free_watch": 0
    },
    "owner": {
        "mid": 23947287,
        "name": "小约翰可汗",
        "face": "https://i0.hdslb.com/bfs/face/85b02cdd864897d9dd2f7e07ddee455594c6359a.jpg"
    },
    "stat": {
        "aid": 335182456,
        "view": 9937522,
        "danmaku": 45891,
        "reply": 14603,
        "favorite": 127785,
        "coin": 347604,
        "share": 66205,
        "now_rank": 0,
        "his_rank": 5,
        "like": 460721,
        "dislike": 0,
        "evaluation": "",
        "argue_msg": "",
        "vt": 0
    },
    "dynamic": "本篇为硬核狠人篇之美国皇帝约翰诺顿。",
    "cid": 507856139,
    "dimension": {
        "width": 1920,
        "height": 1080,
        "rotate": 0
    },
    "season_id": 3491,
    "premiere": null,
    "teenage_mode": 0,
    "is_chargeable_season": false,
    "is_story": false,
    "is_upower_exclusive": false,
    "is_upower_play": false,
    "enable_vt": 0,
    "vt_display": "",
    "no_cache": false,
    "pages": [
        {
            "cid": 507856139,
            "page": 1,
            "from": "vupload",
            "part": "(2)小约翰-美国皇帝",
            "duration": 1357,
            "vid": "",
            "weblink": "",
            "dimension": {
                "width": 1920,
                "height": 1080,
                "rotate": 0
            },
            "first_frame": "http://i1.hdslb.com/bfs/storyff/n220213a2ptkfjk6tqqfu3hi3gajcb6d_firsti.jpg"
        }
    ],
    "subtitle": {
        "allow_submit": false,
        "list": []
    },
    "is_season_display": false,
    "user_garb": {
        "url_image_ani_cut": ""
    },
    "honor_reply": {
        "honor": [
            {
                "aid": 335182456,
                "type": 2,
                "desc": "第128期每周必看",
                "weekly_recommend_num": 128
            },
            {
                "aid": 335182456,
                "type": 3,
                "desc": "全站排行榜最高第5名",
                "weekly_recommend_num": 0
            },
            {
                "aid": 335182456,
                "type": 4,
                "desc": "热门",
                "weekly_recommend_num": 0
            }
        ]
    },
    "like_icon": "",
    "need_jump_bv": false,
    "disable_show_up_info": false
}