{
    "bvid": "BV1M8411p7sK",
    "aid": 221310221,
    "videos": 1,
    "tid": 21,
    "tname": "日常",
    "copyright": 1,
    "pic": "http://i0.hdslb.com/bfs/archive/883206ed45eadbd368ad5513b32cecd0f4c0583b.jpg",
    "title": "今天不做视频了",
    "pubdate": 1671026400,
    "ctime": 1671018912,
    "desc": "出门真快乐！\n更多生活中的凉风请参见→微博@凉风Kaze\n更多活的凉风可以来直播间：http://live.bilibili.com/942101\n求三连！\n求三连！\n求三连！\n求三连！\n求三连！\n求三连！\n求三连！\n求三连！\n求三连！",
    "desc_v2": [
        {
            "raw_text": "出门真快乐！\n更多生活中的凉风请参见→微博@凉风Kaze\n更多活的凉风可以来直播间：http://live.bilibili.com/942101\n求三连！\n求三连！\n求三连！\n求三连！\n求三连！\n求三连！\n求三连！\n求三连！\n求三连！",
            "type": 1,
            "biz_id": 0
        }
    ],
    "state": 0,
    "duration": 448,
    "mission_id": 1088705,
    "rights": {
        "bp": 0,
        "elec": 0,
        "download": 1,
        "movie": 0,
        "pay": 0,
        "hd5": 1,
        "no_reprint": 1,
        "autoplay": 1,
        "ugc_pay": 0,
        "is_cooperation": 0,
        "ugc_pay_preview": 0,
        "no_background": 0,
        "clean_mode": 0,
        "is_stein_gate": 0,
        "is_360": 0,
        "no_share": 0,
        "arc_pay": 0,
        "free_watch": 0
    },
    "owner": {
        "mid": 14110780,
        "name": "凉风Kaze",
        "face": "https://i1.hdslb.com/bfs/face/e0cc906bb531195e9ee9f3b575effdd2b056eaea.jpg"
    },
    "stat": {
        "aid": 221310221,
        "view": 573278,
        "danmaku": 776,
        "reply": 627,
        "favorite": 2081,
        "coin": 5497,
        "share": 442,
        "now_rank": 0,
        "his_rank": 0,
        "like": 65912,
        "dislike": 0,
        "evaluation": "",
        "argue_msg": "",
        "vt": 0
    },
    "dynamic": "出门真快乐！",
    "cid": 923889438,
    "dimension": {
        "width": 3840,
        "height": 2160,
        "rotate": 0
    },
    "premiere": null,
    "teenage_mode": 0,
    "is_chargeable_season": false,
    "is_story": false,
    "is_upower_exclusive": false,
    "is_upower_play": false,
    "enable_vt": 0,
    "vt_display": "",
    "no_cache": false,
    "pages": [
        {
            "cid": 923889438,
            "page": 1,
            "from": "vupload",
            "part": "今天不做视频了",
            "duration": 448,
            "vid": "",
            "weblink": "",
            "dimension": {
                "width": 3840,
                "height": 2160,
                "rotate": 0
            },
            "first_frame": "http://i1.hdslb.com/bfs/storyff/n221214a229j8akh2p26qq3w06qedpxj_firsti.jpg"
        }
    ],
    "subtitle": {
        "allow_submit": false,
        "list": []
    },
    "is_season_display": false,
    "user_garb": {
        "url_image_ani_cut": ""
    },
    "honor_reply": {
        "honor": [
            {
                "aid": 221310221,
                "type": 4,
                "desc": "热门",
                "weekly_recommend_num": 0
            }
        ]
    },
    "like_icon": "",
    "need_jump_bv": false,
    "disable_show_up_info": false
}