{
    "bvid": "BV1Mp4y1h7ii",
    "aid": 972081274,
    "videos": 1,
    "tid": 228,
    "tname": "人文历史",
    "copyright": 1,
    "pic": "http://i1.hdslb.com/bfs/archive/7d4f419aa1e3a4b4fed619a0dff9d9b5c586988b.jpg",
    "title": "人 民 慈 父 杜 瓦 利 埃【奇葩小国13】",
    "pubdate": 1615520459,
    "ctime": 1615520459,
    "desc": "二百年来，海地一直在挑战着人类国家治理的下限。",
    "desc_v2": [
        {
            "raw_text": "二百年来，海地一直在挑战着人类国家治理的下限。",
            "type": 1,
            "biz_id": 0
        }
    ],
    "state": 0,
    "duration": 1417,
    "mission_id": 16646,
    "rights": {
        "bp": 0,
        "elec": 0,
        "download": 1,
        "movie": 0,
        "pay": 0,
        "hd5": 1,
        "no_reprint": 1,
        "autoplay": 1,
        "ugc_pay": 0,
        "is_cooperation": 0,
        "ugc_pay_preview": 0,
        "no_background": 0,
        "clean_mode": 0,
        "is_stein_gate": 0,
        "is_360": 0,
        "no_share": 0,
        "arc_pay": 0,
        "free_watch": 0
    },
    "owner": {
        "mid": 23947287,
        "name": "小约翰可汗",
        "face": "https://i0.hdslb.com/bfs/face/85b02cdd864897d9dd2f7e07ddee455594c6359a.jpg"
    },
    "stat": {
        "aid": 972081274,
        "view": 11517706,
        "danmaku": 47045,
        "reply": 8560,
        "favorite": 45761,
        "coin": 127472,
        "share": 36824,
        "now_rank": 0,
        "his_rank": 0,
        "like": 288927,
        "dislike": 0,
        "evaluation": "",
        "argue_msg": "",
        "vt": 0
    },
    "dynamic": "一个穷到吃土的国家！",
    "cid": 309115424,
    "dimension": {
        "width": 1920,
        "height": 1080,
        "rotate": 0
    },
    "season_id": 665,
    "premiere": null,
    "teenage_mode": 0,
    "is_chargeable_season": false,
    "is_story": false,
    "is_upower_exclusive": false,
    "is_upower_play": false,
    "enable_vt": 0,
    "vt_display": "",
    "no_cache": false,
    "pages": [
        {
            "cid": 309115424,
            "page": 1,
            "from": "vupload",
            "part": "小约翰-人民慈父杜瓦利埃",
            "duration": 1417,
            "vid": "",
            "weblink": "",
            "dimension": {
                "width": 1920,
                "height": 1080,
                "rotate": 0
            }
        }
    ],
    "subtitle": {
        "allow_submit": false,
        "list": []
    },
    "is_season_display": false,
    "user_garb": {
        "url_image_ani_cut": ""
    },
    "honor_reply": {},
    "like_icon": "",
    "need_jump_bv": false,
    "disable_show_up_info": false
}